Metadata-Version: 2.1
Name: xltmpl
Version: 1.0.6
Summary: xltmpl is a package that can append data to excel files without changing worksheets’ style base on openpyxl and xlrd.
Home-page: https://github.com/PyDa5/xltmpl
Author: PyDa5
Author-email: 1174446068@qq.com
License: MIT
Platform: UNKNOWN
Requires: lxml
Requires: openpyxl
Requires: xlwt
Requires: xlrd
Requires: xlutils
Requires: pandas
